geostore/VERSION.md
geostore/__init__.py
geostore/admin.py
geostore/apps.py
geostore/fields.py
geostore/filters.py
geostore/helpers.py
geostore/managers.py
geostore/mixins.py
geostore/models.py
geostore/settings.py
geostore/transformations.py
geostore/urls.py
geostore/validators.py
geostore/views.py
geostore/management/__init__.py
geostore/management/commands/__init__.py
geostore/management/commands/fill_tiles_cache.py
geostore/management/commands/import_csv.py
geostore/management/commands/import_geojson.py
geostore/management/commands/import_osm.py
geostore/management/commands/import_shapefile.py
geostore/management/commands/layer_edit.py
geostore/management/commands/layer_processing.py
geostore/management/commands/mixins.py
geostore/management/commands/update_topology.py
geostore/migrations/0001_initial.py
geostore/migrations/0011_auto_20180711_0831.py
geostore/migrations/0012_extension_pgrouting.py
geostore/migrations/0013_auto_20180919_1146.py
geostore/migrations/0014_auto_20180918_1210.py
geostore/migrations/0015_auto_20181005_1302.py
geostore/migrations/0016_auto_20181120_1059.py
geostore/migrations/0017_auto_20181114_0806.py
geostore/migrations/0018_auto_20190228_1655.py
geostore/migrations/0018_auto_20190326_1049.py
geostore/migrations/0019_merge_20190329_1056.py
geostore/migrations/0020_auto_20190401_1139.py
geostore/migrations/0021_auto_20190415_0945.py
geostore/migrations/0022_auto_20190417_1610.py
geostore/migrations/0023_layer_type_geom.py
geostore/migrations/0024_layer_geom_type.py
geostore/migrations/0025_auto_20190613_1341.py
geostore/migrations/0026_auto_20190613_1529.py
geostore/migrations/0027_layergroup.py
geostore/migrations/0028_remove_layer_group.py
geostore/migrations/__init__.py
geostore/routing/__init__.py
geostore/routing/helpers.py
geostore/serializers/__init__.py
geostore/serializers/geojson.py
geostore/tests/__init__.py
geostore/tests/factories.py
geostore/tests/test_decorators.py
geostore/tests/test_helpers.py
django_geostore-0.3.1.dist-info/METADATA
django_geostore-0.3.1.dist-info/WHEEL
django_geostore-0.3.1.dist-info/top_level.txt
django_geostore-0.3.1.dist-info/RECORD
