Metadata-Version: 2.1
Name: django-geostore
Version: 0.3.1
Summary: Django geographic store and vector tile generation
Home-page: https://github.com/Terralego/django-geostore.git
Author: Makina Corpus
Author-email: terralego-pypi@makina-corpus.com
License: UNKNOWN
Platform: UNKNOWN
Classifier: Environment :: Web Environment
Classifier: Framework :: Django
Classifier: Intended Audience :: Developers
Classifier: Topic :: Internet :: WWW/HTTP
Classifier: Topic :: Internet :: WWW/HTTP :: Dynamic Content
Classifier: License :: OSI Approved :: MIT License
Classifier: Natural Language :: English
Classifier: Operating System :: OS Independent
Classifier: Programming Language :: Python
Classifier: Programming Language :: Python :: 3.6
Classifier: Programming Language :: Python :: 3.7
Requires-Dist: django (<3.0,>=2.1)
Requires-Dist: djangorestframework (>=3.8)
Requires-Dist: djangorestframework-gis (>=0.14)
Requires-Dist: drf-yasg (>=1.9)
Requires-Dist: packaging
Requires-Dist: deepmerge
Requires-Dist: requests (>=2.19)
Requires-Dist: mercantile (>=1.0)
Requires-Dist: psycopg2 (>=2.7)
Requires-Dist: Fiona (>=1.7)
Requires-Dist: Pillow (>=5.3.0)
Requires-Dist: jsonschema (>=3.0)
Provides-Extra: dev
Requires-Dist: factory-boy ; extra == 'dev'
Requires-Dist: flake8 ; extra == 'dev'
Requires-Dist: coverage ; extra == 'dev'
